[{"ws":18,"wg":28,"wd":270,"at":10.1,"fl":10.1,"ap":1018,"cl":93,"p":0.0,"rh":83,"dtl":"2020-05-18T02:00:00+02:00","wah":0.82,"wad":285,"wap":4},{"ws":16,"wg":26,"wd":266,"at":10.4,"fl":10.4,"ap":1018,"cl":100,"p":0.05,"rh":83,"dtl":"2020-05-18T05:00:00+02:00","wah":0.94,"wad":286,"wap":4},{"ws":16,"wg":24,"wd":254,"at":11.1,"fl":11.1,"ap":1018,"cl":100,"p":0.05,"pt":"ra","rh":81,"dtl":"2020-05-18T08:00:00+02:00","wah":0.61,"wad":281,"wap":4},{"ws":12,"wg":19,"wd":242,"at":10.4,"fl":10.4,"ap":1019,"cl":100,"p":1.56,"pt":"ra","rh":92,"dtl":"2020-05-18T11:00:00+02:00","wah":0.51,"wad":272,"wap":3},{"ws":14,"wg":23,"wd":246,"at":10.6,"fl":10.6,"ap":1019,"cl":100,"p":1.89,"pt":"ra","rh":94,"dtl":"2020-05-18T14:00:00+02:00","wah":0.41,"wad":270,"wap":3},{"ws":14,"wg":27,"wd":251,"at":11.8,"fl":11.8,"ap":1018,"cl":100,"p":1.2,"rh":94,"dtl":"2020-05-18T17:00:00+02:00","wah":0.41,"wad":266,"wap":3},{"ws":15,"wg":27,"wd":270,"at":12.5,"fl":12.5,"ap":1017,"cl":99,"p":0.02,"rh":90,"dtl":"2020-05-18T20:00:00+02:00","wah":0.55,"wad":272,"wap":3},{"ws":14,"wg":24,"wd":261,"at":11.8,"fl":11.8,"ap":1018,"cl":100,"p":0.0,"rh":90,"dtl":"2020-05-18T23:00:00+02:00","wah":0.62,"wad":277,"wap":3},{"ws":14,"wg":23,"wd":262,"at":10.8,"fl":10.8,"ap":1018,"cl":100,"p":0.0,"rh":92,"dtl":"2020-05-19T02:00:00+02:00","wah":0.74,"wad":282,"wap":4},{"ws":14,"wg":23,"wd":266,"at":10.5,"fl":10.5,"ap":1017,"cl":100,"p":0.0,"rh":93,"dtl":"2020-05-19T05:00:00+02:00","wah":0.72,"wad":283,"wap":4},{"ws":14,"wg":21,"wd":268,"at":11.6,"fl":11.6,"ap":1017,"cl":94,"p":0.0,"rh":89,"dtl":"2020-05-19T08:00:00+02:00","wah":0.76,"wad":286,"wap":4},{"ws":13,"wg":20,"wd":265,"at":13.3,"fl":13.3,"ap":1017,"cl":90,"p":0.15,"pt":"ra","rh":84,"dtl":"2020-05-19T11:00:00+02:00","wah":0.66,"wad":285,"wap":4},{"ws":15,"wg":22,"wd":288,"at":12.8,"fl":12.8,"ap":1017,"cl":75,"p":0.82,"pt":"ra","rh":88,"dtl":"2020-05-19T14:00:00+02:00","wah":0.65,"wad":297,"wap":4},{"ws":12,"wg":17,"wd":296,"at":13.0,"fl":13.0,"ap":1018,"cl":34,"p":0.19,"rh":79,"dtl":"2020-05-19T17:00:00+02:00","wah":0.5,"wad":297,"wap":3},{"ws":10,"wg":16,"wd":305,"at":12.2,"fl":12.2,"ap":1019,"cl":1,"p":0.0,"rh":77,"dtl":"2020-05-19T20:00:00+02:00","wah":0.44,"wad":300,"wap":3},{"ws":8,"wg":11,"wd":310,"at":10.1,"fl":10.1,"ap":1020,"cl":0,"p":0.0,"rh":83,"dtl":"2020-05-19T23:00:00+02:00","wah":0.4,"wad":307,"wap":3},{"ws":8,"wg":11,"wd":326,"at":9.4,"fl":7.1,"ap":1020,"cl":42,"p":0.0,"rh":88,"dtl":"2020-05-20T02:00:00+02:00","wah":0.35,"wad":309,"wap":3},{"ws":7,"wg":9,"wd":322,"at":8.9,"fl":6.8,"ap":1021,"cl":78,"p":0.0,"rh":85,"dtl":"2020-05-20T05:00:00+02:00","wah":0.34,"wad":313,"wap":3},{"ws":7,"wg":10,"wd":328,"at":10.3,"fl":10.3,"ap":1021,"cl":71,"p":0.0,"rh":77,"dtl":"2020-05-20T08:00:00+02:00","wah":0.29,"wad":315,"wap":3},{"ws":7,"wg":9,"wd":302,"at":11.6,"fl":11.6,"ap":1022,"cl":57,"p":0.0,"rh":70,"dtl":"2020-05-20T11:00:00+02:00","wah":0.2,"wad":313,"wap":3},{"ws":9,"wg":10,"wd":288,"at":12.5,"fl":12.5,"ap":1022,"cl":15,"p":0.0,"rh":68,"dtl":"2020-05-20T14:00:00+02:00","wah":0.14,"wad":313,"wap":3},{"ws":7,"wg":8,"wd":285,"at":12.5,"fl":12.5,"ap":1022,"cl":27,"p":0.0,"rh":71,"dtl":"2020-05-20T17:00:00+02:00","wah":0.11,"wad":313,"wap":3},{"ws":4,"wg":4,"wd":263,"at":11.5,"fl":11.5,"ap":1022,"cl":1,"p":0.0,"rh":79,"dtl":"2020-05-20T20:00:00+02:00","wah":0.1,"wad":313,"wap":3},{"ws":2,"wg":3,"wd":211,"at":9.5,"fl":9.4,"ap":1022,"cl":17,"p":0.0,"rh":86,"dtl":"2020-05-20T23:00:00+02:00","wah":0.09,"wad":310,"wap":3},{"ws":4,"wg":4,"wd":204,"at":9.1,"fl":8.2,"ap":1022,"cl":29,"p":0.0,"rh":88,"dtl":"2020-05-21T02:00:00+02:00","wah":0.09,"wad":305,"wap":4},{"ws":3,"wg":4,"wd":205,"at":8.8,"fl":8.1,"ap":1022,"cl":29,"p":0.0,"rh":91,"dtl":"2020-05-21T05:00:00+02:00","wah":0.09,"wad":297,"wap":3},{"ws":3,"wg":3,"wd":159,"at":11.4,"fl":11.4,"ap":1022,"cl":75,"p":0.0,"rh":86,"dtl":"2020-05-21T08:00:00+02:00","wah":0.17,"wad":305,"wap":2},{"ws":4,"wg":4,"wd":59,"at":13.9,"fl":13.9,"ap":1023,"cl":76,"p":0.1,"pt":"ra","rh":76,"dtl":"2020-05-21T11:00:00+02:00"},{"ws":7,"wg":7,"wd":62,"at":14.6,"fl":14.6,"ap":1023,"cl":74,"p":0.18,"pt":"ra","rh":71,"dtl":"2020-05-21T14:00:00+02:00"},{"ws":11,"wg":12,"wd":72,"at":14.3,"fl":14.3,"ap":1023,"cl":48,"p":0.08,"pt":"ra","rh":75,"dtl":"2020-05-21T17:00:00+02:00"},{"ws":13,"wg":20,"wd":101,"at":11.9,"fl":11.9,"ap":1024,"cl":14,"p":0.08,"rh":76,"dtl":"2020-05-21T20:00:00+02:00"},{"ws":15,"wg":25,"wd":115,"at":9.1,"fl":5.6,"ap":1025,"cl":80,"p":0.0,"rh":63,"dtl":"2020-05-21T23:00:00+02:00"},{"ws":12,"wg":22,"wd":122,"at":8.0,"fl":4.6,"ap":1026,"cl":93,"p":0.0,"rh":58,"dtl":"2020-05-22T02:00:00+02:00"},{"ws":12,"wg":21,"wd":119,"at":7.4,"fl":3.8,"ap":1025,"cl":100,"p":0.0,"rh":52,"dtl":"2020-05-22T05:00:00+02:00"},{"ws":12,"wg":19,"wd":118,"at":8.8,"fl":5.6,"ap":1026,"cl":61,"p":0.0,"rh":58,"dtl":"2020-05-22T08:00:00+02:00"},{"ws":13,"wg":18,"wd":118,"at":12.8,"fl":12.8,"ap":1026,"cl":0,"p":0.0,"rh":54,"dtl":"2020-05-22T11:00:00+02:00"},{"ws":12,"wg":15,"wd":121,"at":14.4,"fl":14.4,"ap":1026,"cl":42,"p":0.0,"rh":57,"dtl":"2020-05-22T14:00:00+02:00"},{"ws":12,"wg":15,"wd":124,"at":14.6,"fl":14.6,"ap":1025,"cl":77,"p":0.0,"rh":58,"dtl":"2020-05-22T17:00:00+02:00"},{"ws":12,"wg":20,"wd":117,"at":12.5,"fl":12.5,"ap":1023,"cl":88,"p":0.0,"rh":71,"dtl":"2020-05-22T20:00:00+02:00"},{"ws":13,"wg":22,"wd":129,"at":10.0,"fl":10.0,"ap":1023,"cl":95,"p":0.0,"rh":71,"dtl":"2020-05-22T23:00:00+02:00"},{"ws":13,"wg":24,"wd":144,"at":10.0,"fl":7.0,"ap":1022,"cl":100,"p":0.0,"rh":62,"dtl":"2020-05-23T02:00:00+02:00"},{"ws":13,"wg":23,"wd":151,"at":10.4,"fl":10.4,"ap":1019,"cl":100,"p":0.0,"rh":59,"dtl":"2020-05-23T05:00:00+02:00"},{"ws":13,"wg":22,"wd":156,"at":11.7,"fl":11.7,"ap":1018,"cl":96,"p":0.0,"rh":67,"dtl":"2020-05-23T08:00:00+02:00"},{"ws":10,"wg":18,"wd":206,"at":10.8,"fl":10.8,"ap":1018,"cl":100,"p":0.55,"pt":"ra","rh":87,"dtl":"2020-05-23T11:00:00+02:00"},{"ws":16,"wg":24,"wd":292,"at":11.6,"fl":11.6,"ap":1020,"cl":100,"p":4.26,"pt":"ra","rh":93,"dtl":"2020-05-23T14:00:00+02:00"},{"ws":10,"wg":18,"wd":264,"at":12.0,"fl":12.0,"ap":1021,"cl":100,"p":0.38,"pt":"ra","rh":92,"dtl":"2020-05-23T17:00:00+02:00"},{"ws":13,"wg":23,"wd":292,"at":12.5,"fl":12.5,"ap":1023,"cl":100,"p":0.11,"pt":"ra","rh":84,"dtl":"2020-05-23T20:00:00+02:00"},{"ws":14,"wg":23,"wd":290,"at":11.2,"fl":11.2,"ap":1025,"cl":100,"p":0.0,"rh":87,"dtl":"2020-05-23T23:00:00+02:00"},{"ws":14,"wg":22,"wd":296,"at":10.2,"fl":10.2,"ap":1027,"cl":37,"p":0.0,"rh":89,"dtl":"2020-05-24T02:00:00+02:00"},{"ws":13,"wg":20,"wd":294,"at":9.8,"fl":6.8,"ap":1028,"cl":0,"p":0.0,"rh":87,"dtl":"2020-05-24T05:00:00+02:00"},{"ws":13,"wg":18,"wd":281,"at":11.1,"fl":11.1,"ap":1029,"cl":0,"p":0.0,"rh":84,"dtl":"2020-05-24T08:00:00+02:00"},{"ws":13,"wg":18,"wd":282,"at":12.8,"fl":12.8,"ap":1030,"cl":50,"p":0.0,"rh":74,"dtl":"2020-05-24T11:00:00+02:00"},{"ws":13,"wg":19,"wd":286,"at":14.2,"fl":14.2,"ap":1030,"cl":36,"p":0.03,"pt":"ra","rh":69,"dtl":"2020-05-24T14:00:00+02:00"},{"ws":14,"wg":22,"wd":290,"at":14.5,"fl":14.5,"ap":1030,"cl":23,"p":0.08,"pt":"ra","rh":75,"dtl":"2020-05-24T17:00:00+02:00"},{"ws":14,"wg":24,"wd":299,"at":13.4,"fl":13.4,"ap":1030,"cl":65,"p":0.05,"rh":83,"dtl":"2020-05-24T20:00:00+02:00"},{"ws":12,"wg":21,"wd":300,"at":12.1,"fl":12.1,"ap":1031,"cl":66,"p":0.1,"rh":91,"dtl":"2020-05-24T23:00:00+02:00"},{"ws":10,"wg":17,"wd":314,"at":11.3,"fl":11.3,"ap":1031,"cl":28,"p":0.01,"rh":94,"dtl":"2020-05-25T02:00:00+02:00"},{"ws":9,"wg":14,"wd":315,"at":10.6,"fl":10.6,"ap":1031,"cl":19,"p":0.0,"rh":94,"dtl":"2020-05-25T05:00:00+02:00"},{"ws":8,"wg":11,"wd":317,"at":12.0,"fl":12.0,"ap":1032,"cl":3,"p":0.0,"rh":89,"dtl":"2020-05-25T08:00:00+02:00"},{"ws":9,"wg":11,"wd":302,"at":13.5,"fl":13.5,"ap":1033,"cl":1,"p":0.0,"rh":82,"dtl":"2020-05-25T11:00:00+02:00"},{"ws":10,"wg":12,"wd":294,"at":14.3,"fl":14.3,"ap":1032,"cl":0,"p":0.0,"rh":79,"dtl":"2020-05-25T14:00:00+02:00"},{"ws":9,"wg":10,"wd":300,"at":14.9,"fl":14.9,"ap":1032,"cl":0,"p":0.0,"rh":76,"dtl":"2020-05-25T17:00:00+02:00"},{"ws":6,"wg":8,"wd":300,"at":14.3,"fl":14.3,"ap":1032,"cl":0,"p":0.0,"rh":80,"dtl":"2020-05-25T20:00:00+02:00"},{"ws":6,"wg":7,"wd":306,"at":12.7,"fl":12.7,"ap":1032,"cl":0,"p":0.0,"rh":84,"dtl":"2020-05-25T23:00:00+02:00"},{"ws":6,"wg":8,"wd":326,"at":12.1,"fl":12.1,"ap":1032,"cl":22,"p":0.0,"rh":90,"dtl":"2020-05-26T02:00:00+02:00"},{"ws":5,"wg":6,"wd":317,"at":11.7,"fl":11.7,"ap":1032,"cl":86,"p":0.0,"rh":90,"dtl":"2020-05-26T05:00:00+02:00"},{"ws":6,"wg":7,"wd":297,"at":13.4,"fl":13.4,"ap":1032,"cl":0,"p":0.0,"rh":84,"dtl":"2020-05-26T08:00:00+02:00"},{"ws":7,"wg":8,"wd":285,"at":14.6,"fl":14.6,"ap":1032,"cl":0,"p":0.0,"rh":77,"dtl":"2020-05-26T11:00:00+02:00"},{"ws":6,"wg":8,"wd":291,"at":15.3,"fl":15.3,"ap":1032,"cl":11,"p":0.0,"rh":71,"dtl":"2020-05-26T14:00:00+02:00"},{"ws":6,"wg":7,"wd":292,"at":15.7,"fl":15.7,"ap":1031,"cl":34,"p":0.0,"rh":68,"dtl":"2020-05-26T17:00:00+02:00"},{"ws":5,"wg":6,"wd":286,"at":14.7,"fl":14.7,"ap":1031,"cl":43,"p":0.0,"rh":74,"dtl":"2020-05-26T20:00:00+02:00"},{"ws":7,"wg":9,"wd":354,"at":12.4,"fl":12.4,"ap":1031,"cl":91,"p":0.0,"rh":88,"dtl":"2020-05-26T23:00:00+02:00"},{"ws":6,"wg":7,"wd":345,"at":11.7,"fl":11.7,"ap":1031,"cl":99,"p":0.0,"rh":91,"dtl":"2020-05-27T02:00:00+02:00"},{"ws":6,"wg":8,"wd":16,"at":10.9,"fl":10.9,"ap":1031,"cl":33,"p":0.0,"rh":85,"dtl":"2020-05-27T05:00:00+02:00"},{"ws":6,"wg":8,"wd":18,"at":12.1,"fl":12.1,"ap":1031,"cl":12,"p":0.0,"rh":75,"dtl":"2020-05-27T08:00:00+02:00"},{"ws":4,"wg":4,"wd":356,"at":13.5,"fl":13.5,"ap":1031,"cl":9,"p":0.0,"rh":65,"dtl":"2020-05-27T11:00:00+02:00"},{"ws":5,"wg":5,"wd":349,"at":14.5,"fl":14.5,"ap":1030,"cl":24,"p":0.0,"rh":62,"dtl":"2020-05-27T14:00:00+02:00"},{"ws":4,"wg":4,"wd":20,"at":14.9,"fl":14.9,"ap":1029,"cl":30,"p":0.0,"rh":60,"dtl":"2020-05-27T17:00:00+02:00"},{"ws":6,"wg":9,"wd":77,"at":13.5,"fl":13.5,"ap":1027,"cl":1,"p":0.0,"rh":71,"dtl":"2020-05-27T20:00:00+02:00"},{"ws":8,"wg":12,"wd":122,"at":10.7,"fl":10.7,"ap":1026,"cl":0,"p":0.0,"rh":79,"dtl":"2020-05-27T23:00:00+02:00"}]
